promy/__init__.py
promy/apps.py
promy/internal/__init__.py
promy/internal/health_check.py
promy/internal/views.py
promy/management/__init__.py
promy/management/commands/__init__.py
promy/management/commands/consume.py
promy/management/commands/export_periodic_tasks.py
promy/management/commands/prom_setup.py
promy/management/commands/serve_metrics.py
promy/migrations/__init__.py
promy/models.py
promy/settings/__init__.py
promy/settings/env.py
promy/settings/setup.py
promy/station/__init__.py
promy/station/consts.py
promy/station/publish.py
promy/station/registry.py
promy/station/updater.py
promy/station/views.py
promy/tasks.py
promy/urls.py
promy/utils/__init__.py
promy/utils/cache.py
promy/utils/celery.py
promy/utils/django.py
promy/utils/exception.py
promy/utils/http.py
promy/utils/http_requests.py
promy/utils/kafka.py
promy/utils/metrics/__init__.py
promy/utils/metrics/logs.py
promy/utils/models.py
promy/utils/monitoring.py
promy/utils/numbers.py
promy/utils/paginations.py
promy/utils/periodic_tasks.py
promy/utils/python.py
promy/utils/rate_limit.py
promy/utils/redis.py
promy/utils/sentry.py
promy/utils/serializers.py
promy/utils/time.py
promy/utils/tracing.py
promy/utils/views.py
promy-0.1.7.dist-info/METADATA
promy-0.1.7.dist-info/WHEEL
promy-0.1.7.dist-info/RECORD
