Metadata-Version: 2.3
Name: promy
Version: 0.1.7
Summary: A library for promy people
Requires-Python: >=3.11,<4.0
Classifier: Programming Language :: Python :: 3
Classifier: Programming Language :: Python :: 3.11
Classifier: Programming Language :: Python :: 3.12
Classifier: Programming Language :: Python :: 3.13
Requires-Dist: black (>=25.1.0,<26.0.0)
Requires-Dist: boto3 (>=1.36.24,<2.0.0)
Requires-Dist: celery (>=5.4.0,<6.0.0)
Requires-Dist: deprecated (>=1.2.18,<2.0.0)
Requires-Dist: django (>=5.1.6,<6.0.0)
Requires-Dist: django-celery-beat (>=2.7.0,<3.0.0)
Requires-Dist: django-celery-results (>=2.5.1,<3.0.0)
Requires-Dist: django-prometheus (>=2.3.1,<3.0.0)
Requires-Dist: django-stubs (>=5.1.3,<6.0.0)
Requires-Dist: djangorestframework (>=3.15.2,<4.0.0)
Requires-Dist: kafka-python (>=2.0.3,<3.0.0)
Requires-Dist: mypy (>=1.15.0,<2.0.0)
Requires-Dist: opentelemetry-api (>=1.30.0,<2.0.0)
Requires-Dist: opentelemetry-exporter-otlp-proto-common (>=1.30.0,<2.0.0)
Requires-Dist: opentelemetry-exporter-otlp-proto-http (>=1.30.0,<2.0.0)
Requires-Dist: opentelemetry-sdk (>=1.30.0,<2.0.0)
Requires-Dist: pre-commit (>=4.1.0,<5.0.0)
Requires-Dist: psycopg2 (>=2.9.10,<3.0.0)
Requires-Dist: psycopg2-binary (>=2.9.10,<3.0.0)
Requires-Dist: pydantic (>=2.10.6,<3.0.0)
Requires-Dist: pydantic-settings (>=2.7.1,<3.0.0)
Requires-Dist: redis (>=5.2.1,<6.0.0)
Requires-Dist: requests (>=2.32.3,<3.0.0)
Requires-Dist: rich (>=13.9.4,<14.0.0)
Requires-Dist: sentry-sdk (>=2.22.0,<3.0.0)
Requires-Dist: setuptools (>=75.8.0,<76.0.0)
Requires-Dist: twine (>=6.1.0,<7.0.0)
Requires-Dist: urllib3 (>=2.3.0,<3.0.0)
Requires-Dist: wheel (>=0.45.1,<0.46.0)
